snipster/Snippet.py
snipster/SnippetList.py
snipster/Sourcer.py
snipster/__main__.py
snipster/globalVars.py
snipster_py-1.0.3.dist-info/METADATA
snipster_py-1.0.3.dist-info/RECORD
snipster_py-1.0.3.dist-info/WHEEL
snipster_py-1.0.3.dist-info/entry_points.txt
snipster_py-1.0.3.dist-info/top_level.txt
