Metadata-Version: 2.1
Name: snipster-py
Version: 1.0.3
Summary: A simple command line snippet manager
Home-page: https://github.com/sophieau/snipster
Author: Sophie Au
Author-email: some.person@web.de
License: MIT
Keywords: snippet,snippets-manager,command-line-tool
Platform: UNKNOWN
Requires-Python: >=3.6
Requires-Dist: Pygments (>=2.2.0)
Requires-Dist: pyperclip (>=1.6.0)
Requires-Dist: tabulate (>=0.8.2)
